README.md
setup.py
aws_parameter_store/__init__.py
aws_parameter_store/aws_parameter_store.py
aws_parameter_store.egg-info/PKG-INFO
aws_parameter_store.egg-info/SOURCES.txt
aws_parameter_store.egg-info/dependency_links.txt
aws_parameter_store.egg-info/requires.txt
aws_parameter_store.egg-info/top_level.txt