Metadata-Version: 2.1
Name: aws-parameter-store
Version: 0.0.1
Summary: AWS SSM parameter store client that constructs nested dictionary out of hierarchical path
Home-page: https://github.com/Vonage/aws-parameter-store-py
Author: Amit Zigelman
Author-email: amit.zigelman@vonage.com
License: apache-2.0
Keywords: AWS,SSM,PARAMETER,PARAMETER STORE
Platform: UNKNOWN
Classifier: Programming Language :: Python :: 3
